MUX/design.v
module mux (A,B,S,Y);
    input A, B, S;   // inputs
    output Y;         // output
    // Corrected assign statement
    assign Y = (S) ? B : A;  
endmodule

MUX/testbench.v
module tb ();
//declaring inputs
  reg A,B,S;
//declaring outputs
 wire Y;
//instantiating the design module
    mux dut (
        .A(A),
        .B(B),
        .S(S),
        .Y(Y)
    );
//providing stimulus
    initial begin
        //test case 1
        A<=1'b0; B<=1'b0; S<=1'b0;
        #100; //delay in output
        //test case 2
        A<=1'b0; B<=1'b0; S<=1'b1;
        #100;
        //test case 3
        A<=1'b0; B<=1'b1; S<=1'b0;
        #100;
        //test case 4
        A<=1'b0; B<=1'b1; S<=1'b1;
        #100;
        //test case 5
        A<=1'b1; B<=1'b0; S<=1'b0;
        #100;
        //test case 6
        A<=1'b1; B<=1'b0; S<=1'b1;
        #100;
        //test case 7
        A<=1'b1; B<=1'b1; S<=1'b0;
        #100;
        //test case 8
        A<=1'b1; B<=1'b1; S<=1'b1;
        #100;
    end
//dump waveform
    initial begin   
        $dumpfile("mux.vcd");
        $dumpvars(0,tb); //dump all signals inside testbench
end   
endmodule

MUX/mux.vcd
$date
	Sun Sep 28 11:11:54 2025
$end
$version
	Icarus Verilog
$end
$timescale
	1s
$end
$scope module tb $end
$var wire 1 ! Y $end
$var reg 1 " A $end
$var reg 1 # B $end
$var reg 1 $ S $end
$scope module dut $end
$var wire 1 " A $end
$var wire 1 # B $end
$var wire 1 $ S $end
$var wire 1 ! Y $end
$upscope $end
$upscope $end
$enddefinitions $end
$comment Show the parameter values. $end
$dumpall
$end
#0
$dumpvars
0$
0#
0"
0!
$end
#100
1$
#200
0$
1#
#300
1!
1$
#400
0$
0#
1"
#500
0!
1$
#600
1!
0$
1#
#700
1$
