Combinational_circuit/comb/design.v
module comb (A,B,C,Q);

//declaring inputs
input A,B,C;
//declaring output
output Q ;
//declaring internal signals
wire A_NAND_B,A_NOR_B;
//assign statement

assign A_NAND_B = ~(A & B);
assign A_NOR_B = ~(A | B);

assign Q = (C) & (A_NAND_B) & (A_NOR_B);

endmodule

Combinational_circuit/comb/testbench.v
module tb ();
//declaring inputs
  reg A,B,C;
//declaring outputs
  wire Q;   
//design call
    comb dut (
        .A(A),
        .B(B),
        .C(C),
        .Q(Q)
    );

//providing stimulus    
    initial begin
        //test case 1
        A<=1'b0; B<=1'b0; C<=1'b0;
        #100; //delay in output
        //test case 2
        A<=1'b0; B<=1'b0; C<=1'b1;
        #100;
        //test case 3
        A<=1'b0; B<=1'b1; C<=1'b0;
        #100;
        //test case 4
        A<=1'b0; B<=1'b1; C<=1'b1;
        #100;
        //test case 5
        A<=1'b1; B<=1'b0; C<=1'b0;
        #100;
        //test case 6
        A<=1'b1; B<=1'b0; C<=1'b1;
        #100;
        //test case 7
        A<=1'b1; B<=1'b1; C<=1'b0;
        #100;
        //test case 8
        A<=1'b1; B<=1'b1; C<=1'b1;
        #100;
    end

//dump waveform
    initial begin
        $dumpfile("comb.vcd");
        $dumpvars(0,tb); //dump all signals inside testbench
end   
endmodule

Combinational_circuit/comb/comb.vcd
$date
	Sun Sep 28 10:53:55 2025
$end
$version
	Icarus Verilog
$end
$timescale
	1s
$end
$scope module tb $end
$var wire 1 ! Q $end
$var reg 1 " A $end
$var reg 1 # B $end
$var reg 1 $ C $end
$scope module dut $end
$var wire 1 " A $end
$var wire 1 % A_NAND_B $end
$var wire 1 & A_NOR_B $end
$var wire 1 # B $end
$var wire 1 $ C $end
$var wire 1 ! Q $end
$upscope $end
$upscope $end
$enddefinitions $end
$comment Show the parameter values. $end
$dumpall
$end
#0
$dumpvars
1&
1%
0$
0#
0"
0!
$end
#100
1!
1$
#200
0!
0&
0$
1#
#300
1$
#400
0$
0#
1"
#500
1$
#600
0%
0$
1#
#700
1$
