Combinational_circuit/design.v
module comb(S,P,V,LED);
//declaring inputs
input S,P,V;
//declaring output
output LED ;

//assign statement
assign LED = (~S) & (P) & (V);

endmodule

Combinational_circuit/testbench.v
module tb ();
//declaring inputs
  reg S,P,V;    
//declaring outputs
  wire LED;
//design call
    comb dut (
        .S(S),
        .P(P),
        .V(V),
        .LED(LED)
    );
//providing stimulus
  initial begin
    //test case 1
    S<=1'b0; P<=1'b0; V<=1'b0;
    #100; //delay in output
    //test case 2
    S<=1'b0; P<=1'b0; V<=1'b1;
    #100;
    //test case 3
    S<=1'b0; P<=1'b1; V<=1'b0;
    #100;
    //test case 4
    S<=1'b0; P<=1'b1; V<=1'b1;
    #100;
    //test case 5
    S<=1'b1; P<=1'b0; V<=1'b0;
    #100;
    //test case 6
    S<=1'b1; P<=1'b0; V<=1'b1;
    #100;
    //test case 7
    S<=1'b1; P<=1'b1; V<=1'b0;
    #100;
    //test case 8
    S<=1'b1; P<=1'b1; V<=1'b1;
    #100;
  end

//dump waveform
    initial begin
        $dumpfile("comb.vcd");
        $dumpvars(0,tb); //dump all signals inside testbench
end
endmodule

Combinational_circuit/comb.vcd
$date
	Sun Sep 28 10:37:42 2025
$end
$version
	Icarus Verilog
$end
$timescale
	1s
$end
$scope module tb $end
$var wire 1 ! LED $end
$var reg 1 " P $end
$var reg 1 # S $end
$var reg 1 $ V $end
$scope module dut $end
$var wire 1 ! LED $end
$var wire 1 " P $end
$var wire 1 # S $end
$var wire 1 $ V $end
$upscope $end
$upscope $end
$enddefinitions $end
$comment Show the parameter values. $end
$dumpall
$end
#0
$dumpvars
0$
0#
0"
0!
$end
#100
1$
#200
0$
1"
#300
1!
1$
#400
0!
0$
0"
1#
#500
1$
#600
0$
1"
#700
1$
